polyaxon_nginx/__init__.py
polyaxon_nginx/generate.py
polyaxon_nginx/settings.py
polyaxon_nginx/schemas/__init__.py
polyaxon_nginx/schemas/base.py
polyaxon_nginx/schemas/buffering.py
polyaxon_nginx/schemas/charset.py
polyaxon_nginx/schemas/error_page.py
polyaxon_nginx/schemas/gzip.py
polyaxon_nginx/schemas/listen.py
polyaxon_nginx/schemas/locations.py
polyaxon_nginx/schemas/logging.py
polyaxon_nginx/schemas/main.py
polyaxon_nginx/schemas/plugins.py
polyaxon_nginx/schemas/polyaxon.py
polyaxon_nginx/schemas/redirect.py
polyaxon_nginx/schemas/ssl.py
polyaxon_nginx/schemas/timeout.py
polyaxon_nginx/schemas/uwsgi.py
polyaxon_nginx/schemas/ws.py
tests/__init__.py
tests/test_defaults.py
tests/test_generate.py
tests/test_main.py
tests/test_polyaxon.py
tests/test_schemas.py
polyaxon_nginx-0.5.5.dist-info/LICENSE
polyaxon_nginx-0.5.5.dist-info/METADATA
polyaxon_nginx-0.5.5.dist-info/WHEEL
polyaxon_nginx-0.5.5.dist-info/top_level.txt
polyaxon_nginx-0.5.5.dist-info/RECORD
