Metadata-Version: 2.1
Name: polyaxon-nginx
Version: 0.5.5
Summary: Polyaxon nginx conf generator.
Home-page: https://github.com/polyaxon/polyaxon-nginx
Author: Mourad Mourafiq
Author-email: mourad@polyaxon.com
Maintainer: Mourad Mourafiq
Maintainer-email: mourad@polyaxon.com
License: MIT
Keywords: polyaxon,nginx,micro-service,docker,containers,kubernetes
Platform: any
Classifier: Programming Language :: Python
Classifier: Operating System :: OS Independent
Classifier: Intended Audience :: Developers
Classifier: Intended Audience :: Science/Research
Classifier: Topic :: Scientific/Engineering :: Artificial Intelligence
